worldpops/__init__.py
worldpops/country_info.py
worldpops/index.py
worldpops/world.py
worldpops-2.dist-info/LICENSE
worldpops-2.dist-info/METADATA
worldpops-2.dist-info/WHEEL
worldpops-2.dist-info/top_level.txt
worldpops-2.dist-info/RECORD
