Metadata-Version: 2.1
Name: worldpops
Version: 2
Summary: Get live population, population rank, yearly change, and density of any country.
Home-page: https://github.com/gadhagod/worldpops
Author: GadhaGod
Author-email: gadhaguy13@gmail.com
License: UNKNOWN
Platform: UNKNOWN
Classifier: Programming Language :: Python :: 3
Classifier: License :: OSI Approved :: MIT License
Classifier: Operating System :: OS Independent
Requires-Python: >=3.6
Requires-Dist: requests
